README.rst
setup.py
nrv/__init__.py
nrv/utils.py
nrv/v1.py
nrv/v2.py
nrv/v3.py
nrv.egg-info/PKG-INFO
nrv.egg-info/SOURCES.txt
nrv.egg-info/dependency_links.txt
nrv.egg-info/not-zip-safe
nrv.egg-info/requires.txt
nrv.egg-info/top_level.txt