Metadata-Version: 2.1
Name: nrv
Version: 0.2.1
Summary: Network Resource Vocabulary.
Home-page: https://gitlab.com/wefindx/nrv
Author: Mindey
Author-email: mindey@qq.com
License: MIT
Platform: UNKNOWN
Provides-Extra: test
